AUTHORS.rst
CHANGES.rst
LICENSE.txt
MANIFEST.in
README.md
README.rst
TODO.rst
setup.py
django_joyride.egg-info/PKG-INFO
django_joyride.egg-info/SOURCES.txt
django_joyride.egg-info/dependency_links.txt
django_joyride.egg-info/not-zip-safe
django_joyride.egg-info/requires.txt
django_joyride.egg-info/top_level.txt
joyride/__init__.py
joyride/admin.py
joyride/models.py
joyride/settings.py
joyride/utils.py
joyride/static/joyride/css/joyride-2.1.css
joyride/static/joyride/js/jquery-1.10.1.js
joyride/static/joyride/js/jquery.cookie.js
joyride/static/joyride/js/jquery.joyride-2.1.js
joyride/static/joyride/js/modernizr.mq.js
joyride/templates/joyride/include_all.html
joyride/templates/joyride/include_css.html
joyride/templates/joyride/include_js.html
joyride/templates/joyride/joyride.html
joyride/templates/joyride/joyride_script.html
joyride/templates/joyride/joyrides.html
joyride/templatetags/__init__.py
joyride/templatetags/joyride_tags.py